[
    {
        "chunk_id": "3bc28b7b-0d6b-4249-9028-08076c4affc8",
        "document_id": "c0dbd3f2-a036-4e0d-98ae-62a5927543ec",
        "chunk_number": 1,
        "text": "SmartDocs Enterprise Policy Document Section 1: Annual Leave & Remote Work Policy Employees are entitled to 25 days of paid annual leave per calendar year. Remote work is permitted up to 3 days per week with manager approval. Section 2: Information Security & Air-Gapped Compliance",
        "word_count": 45,
        "character_count": 281
    }
]